discord/ext/prettyhelp/__init__.py
discord/ext/prettyhelp/menu.py
discord/ext/prettyhelp/permission_utils.py
discord/ext/prettyhelp/pretty_help.py
discord_ext_prettyhelp-0.2.3.dist-info/LICENSE
discord_ext_prettyhelp-0.2.3.dist-info/METADATA
discord_ext_prettyhelp-0.2.3.dist-info/WHEEL
discord_ext_prettyhelp-0.2.3.dist-info/top_level.txt
discord_ext_prettyhelp-0.2.3.dist-info/RECORD
