Metadata-Version: 2.1
Name: discord-ext-prettyhelp
Version: 0.2.3
Summary: A pretty embeded version of the default help command.
Home-page: https://github.com/CircuitsBots/discord-ext-prettyhelp
Author: Circuit
License: MIT
Platform: UNKNOWN
Requires-Python: >=3.5.3
Requires-Dist: discord.py (>=1.2.5)
